INSTALL.rst
LICENSE
MANIFEST.in
README.rst
VERSION
requirements.txt
setup.cfg
setup.py
tasks.py
src/boogie/__init__.py
src/boogie/__main__.py
src/boogie/__meta__.py
src/boogie/manager.py
src/boogie/models.py
src/boogie/query.py
src/boogie/router.py
src/boogie.egg-info/PKG-INFO
src/boogie.egg-info/SOURCES.txt
src/boogie.egg-info/dependency_links.txt
src/boogie.egg-info/not-zip-safe
src/boogie.egg-info/requires.txt
src/boogie.egg-info/top_level.txt
src/boogie/tests/__init__.py
src/boogie/tests/_test_documentation.py
src/boogie/tests/conftest.py
src/boogie/tests/test_boogie.py
src/boogie/tests/test_queryset.py
src/boogie/tests/testapp/__init__.py
src/boogie/tests/testapp/admin.py
src/boogie/tests/testapp/apps.py
src/boogie/tests/testapp/models.py
src/boogie/tests/testapp/tests.py
src/boogie/tests/testapp/views.py
src/boogie/tests/testapp/migrations/0001_initial.py
src/boogie/tests/testapp/migrations/__init__.py
src/boogie/tests/testproject/__init__.py
src/boogie/tests/testproject/settings.py
src/boogie/tests/testproject/urls.py
src/boogie/tests/testproject/wsgi.py
src/boogie/types/__init__.py
src/boogie/types/attrlist.py